{
  "generatedAt": "2026-06-03T18:01:54.833Z",
  "total": 1000,
  "complete": 20,
  "pending": 1000,
  "needsReview": 0,
  "coverage": [
    {
      "field": "photo_url",
      "dbKey": "photo_url",
      "count": 30,
      "pct": 3
    },
    {
      "field": "club",
      "dbKey": "club",
      "count": 35,
      "pct": 3.5
    },
    {
      "field": "shirt_number",
      "dbKey": "shirt_number",
      "count": 27,
      "pct": 2.7
    },
    {
      "field": "height",
      "dbKey": "height",
      "count": 27,
      "pct": 2.7
    },
    {
      "field": "preferred_foot",
      "dbKey": "preferred_foot",
      "count": 22,
      "pct": 2.2
    },
    {
      "field": "market_value",
      "dbKey": "market_value",
      "count": 6,
      "pct": 0.6
    },
    {
      "field": "birth_date",
      "dbKey": "date_of_birth",
      "count": 1000,
      "pct": 100
    },
    {
      "field": "nationality",
      "dbKey": "nationality",
      "count": 998,
      "pct": 99.8
    },
    {
      "field": "position",
      "dbKey": "position",
      "count": 1000,
      "pct": 100
    }
  ],
  "worstTeams": [
    {
      "teamId": "bb5642a4-c733-4801-90f1-5e4b3cd8f293",
      "teamName": "Haiti",
      "players": 24,
      "avgQuality": 20,
      "incomplete": 24
    },
    {
      "teamId": "b11040ed-0acf-43c2-932f-478baf0c22f7",
      "teamName": "Germany",
      "players": 26,
      "avgQuality": 20,
      "incomplete": 26
    },
    {
      "teamId": "944474ac-2102-4033-9275-195ff11c9b4b",
      "teamName": "Spain",
      "players": 26,
      "avgQuality": 20,
      "incomplete": 26
    },
    {
      "teamId": "2c36be30-d96e-45ff-aa82-f5bb6bb9d746",
      "teamName": "Paraguay",
      "players": 26,
      "avgQuality": 20,
      "incomplete": 26
    },
    {
      "teamId": "09f42c00-65ed-47f2-9391-d47f879d1a75",
      "teamName": "Argentina",
      "players": 26,
      "avgQuality": 20,
      "incomplete": 26
    },
    {
      "teamId": "518413de-7725-48c5-a17e-c3a8d2d0368e",
      "teamName": "Brazil",
      "players": 26,
      "avgQuality": 20,
      "incomplete": 26
    },
    {
      "teamId": "82032bc1-b59c-493a-b604-88628df78627",
      "teamName": "Portugal",
      "players": 26,
      "avgQuality": 20,
      "incomplete": 26
    },
    {
      "teamId": "282e5bcd-01e5-4b07-a44a-6f469662dbfe",
      "teamName": "Japan",
      "players": 26,
      "avgQuality": 20,
      "incomplete": 26
    },
    {
      "teamId": "ab4f6ae8-4b80-47fc-a8cc-ca8d11532b08",
      "teamName": "Mexico",
      "players": 26,
      "avgQuality": 20,
      "incomplete": 26
    },
    {
      "teamId": "8d8a9c00-18b0-4778-b6e2-600700a1d916",
      "teamName": "England",
      "players": 26,
      "avgQuality": 20,
      "incomplete": 26
    },
    {
      "teamId": "9441db50-b67a-4666-8c20-5eb82df436e2",
      "teamName": "United States",
      "players": 26,
      "avgQuality": 20,
      "incomplete": 26
    },
    {
      "teamId": "2911e712-934b-4228-ba1c-c48fe67ef17d",
      "teamName": "South Korea",
      "players": 25,
      "avgQuality": 20,
      "incomplete": 25
    }
  ],
  "topIncomplete": [
    {
      "id": "c46c3b6b-af01-4857-ba5e-683704455c45",
      "name": "Yassine Chikhaoui",
      "team_id": "1ec8cecf-ce3d-4f76-9d5a-db707f285be0",
      "provider": "football_data",
      "provider_player_id": "173578",
      "photo_url": null,
      "club": null,
      "shirt_number": null,
      "height": null,
      "preferred_foot": null,
      "market_value": null,
      "market_value_eur": null,
      "rating": null,
      "date_of_birth": "2004-06-09",
      "nationality": null,
      "position": "Defence",
      "data_quality_score": 15,
      "enrichment_status": "pending",
      "data_sources": {},
      "missing": 7,
      "score": 15
    },
    {
      "id": "c5f0fe47-842f-4c79-bcb8-e9c543de7e82",
      "name": "Carlens Arcus",
      "team_id": "bb5642a4-c733-4801-90f1-5e4b3cd8f293",
      "provider": "football_data",
      "provider_player_id": "532",
      "photo_url": null,
      "club": null,
      "shirt_number": null,
      "height": null,
      "preferred_foot": null,
      "market_value": null,
      "market_value_eur": null,
      "rating": null,
      "date_of_birth": "1996-06-28",
      "nationality": "Haiti",
      "position": "Defence",
      "data_quality_score": 20,
      "enrichment_status": "pending",
      "data_sources": {},
      "missing": 6,
      "score": 20
    },
    {
      "id": "69b21d8c-6285-458f-9322-5f9022c3ae13",
      "name": "Ibrahim Sabra",
      "team_id": "0a828293-51b2-478d-9f4e-e7a6f87619c3",
      "provider": "football_data",
      "provider_player_id": "280317",
      "photo_url": null,
      "club": null,
      "shirt_number": null,
      "height": null,
      "preferred_foot": null,
      "market_value": null,
      "market_value_eur": null,
      "rating": null,
      "date_of_birth": "2006-02-01",
      "nationality": "Jordan",
      "position": "Offence",
      "data_quality_score": 20,
      "enrichment_status": "pending",
      "data_sources": {},
      "missing": 6,
      "score": 20
    },
    {
      "id": "b1256a89-78b4-4fc7-8118-aad6908fef60",
      "name": "Fernando Muslera",
      "team_id": "2c14696e-6656-4cd7-86c3-a1a3cf19ee5f",
      "provider": "football_data",
      "provider_player_id": "3160",
      "photo_url": null,
      "club": null,
      "shirt_number": null,
      "height": null,
      "preferred_foot": null,
      "market_value": null,
      "market_value_eur": null,
      "rating": null,
      "date_of_birth": "1986-06-16",
      "nationality": "Uruguay",
      "position": "Goalkeeper",
      "data_quality_score": 20,
      "enrichment_status": "pending",
      "data_sources": {},
      "missing": 6,
      "score": 20
    },
    {
      "id": "9a7bb783-5aa6-4059-823a-0f84c5e5a174",
      "name": "Santiago Mele",
      "team_id": "2c14696e-6656-4cd7-86c3-a1a3cf19ee5f",
      "provider": "football_data",
      "provider_player_id": "30210",
      "photo_url": null,
      "club": null,
      "shirt_number": null,
      "height": null,
      "preferred_foot": null,
      "market_value": null,
      "market_value_eur": null,
      "rating": null,
      "date_of_birth": "1997-09-06",
      "nationality": "Uruguay",
      "position": "Goalkeeper",
      "data_quality_score": 20,
      "enrichment_status": "pending",
      "data_sources": {},
      "missing": 6,
      "score": 20
    },
    {
      "id": "cfe64799-5ab7-458c-8023-317c9346ed3c",
      "name": "Sergio Rochet",
      "team_id": "2c14696e-6656-4cd7-86c3-a1a3cf19ee5f",
      "provider": "football_data",
      "provider_player_id": "30386",
      "photo_url": null,
      "club": null,
      "shirt_number": null,
      "height": null,
      "preferred_foot": null,
      "market_value": null,
      "market_value_eur": null,
      "rating": null,
      "date_of_birth": "1993-03-23",
      "nationality": "Uruguay",
      "position": "Goalkeeper",
      "data_quality_score": 20,
      "enrichment_status": "pending",
      "data_sources": {},
      "missing": 6,
      "score": 20
    },
    {
      "id": "3e556aa8-407e-46d4-84f3-27ef60636626",
      "name": "Guillermo Varela",
      "team_id": "2c14696e-6656-4cd7-86c3-a1a3cf19ee5f",
      "provider": "football_data",
      "provider_player_id": "3165",
      "photo_url": null,
      "club": null,
      "shirt_number": null,
      "height": null,
      "preferred_foot": null,
      "market_value": null,
      "market_value_eur": null,
      "rating": null,
      "date_of_birth": "1993-03-24",
      "nationality": "Uruguay",
      "position": "Defence",
      "data_quality_score": 20,
      "enrichment_status": "pending",
      "data_sources": {},
      "missing": 6,
      "score": 20
    },
    {
      "id": "f876faf0-4139-4794-9c31-45caa64b70e1",
      "name": "Ronald Araújo",
      "team_id": "2c14696e-6656-4cd7-86c3-a1a3cf19ee5f",
      "provider": "football_data",
      "provider_player_id": "28292",
      "photo_url": null,
      "club": null,
      "shirt_number": null,
      "height": null,
      "preferred_foot": null,
      "market_value": null,
      "market_value_eur": null,
      "rating": null,
      "date_of_birth": "1999-03-07",
      "nationality": "Uruguay",
      "position": "Defence",
      "data_quality_score": 20,
      "enrichment_status": "pending",
      "data_sources": {},
      "missing": 6,
      "score": 20
    },
    {
      "id": "296fbb62-9f55-42d7-a73f-389f80373e72",
      "name": "Sebastían Cáceres",
      "team_id": "2c14696e-6656-4cd7-86c3-a1a3cf19ee5f",
      "provider": "football_data",
      "provider_player_id": "28326",
      "photo_url": null,
      "club": null,
      "shirt_number": null,
      "height": null,
      "preferred_foot": null,
      "market_value": null,
      "market_value_eur": null,
      "rating": null,
      "date_of_birth": "1999-08-18",
      "nationality": "Uruguay",
      "position": "Defence",
      "data_quality_score": 20,
      "enrichment_status": "pending",
      "data_sources": {},
      "missing": 6,
      "score": 20
    },
    {
      "id": "55afbb05-1e4b-4cae-813b-36d2504b6ffa",
      "name": "Matías Viña",
      "team_id": "2c14696e-6656-4cd7-86c3-a1a3cf19ee5f",
      "provider": "football_data",
      "provider_player_id": "28426",
      "photo_url": null,
      "club": null,
      "shirt_number": null,
      "height": null,
      "preferred_foot": null,
      "market_value": null,
      "market_value_eur": null,
      "rating": null,
      "date_of_birth": "1997-11-09",
      "nationality": "Uruguay",
      "position": "Defence",
      "data_quality_score": 20,
      "enrichment_status": "pending",
      "data_sources": {},
      "missing": 6,
      "score": 20
    },
    {
      "id": "0c62b9f5-e7ad-4c77-bb97-700c42d33b0e",
      "name": "Joaquín Piquerez",
      "team_id": "2c14696e-6656-4cd7-86c3-a1a3cf19ee5f",
      "provider": "football_data",
      "provider_player_id": "28740",
      "photo_url": null,
      "club": null,
      "shirt_number": null,
      "height": null,
      "preferred_foot": null,
      "market_value": null,
      "market_value_eur": null,
      "rating": null,
      "date_of_birth": "1998-08-24",
      "nationality": "Uruguay",
      "position": "Defence",
      "data_quality_score": 20,
      "enrichment_status": "pending",
      "data_sources": {},
      "missing": 6,
      "score": 20
    },
    {
      "id": "a16320c5-4d6c-4874-93e3-a5d5814bb54d",
      "name": "Maximiliano Araújo",
      "team_id": "2c14696e-6656-4cd7-86c3-a1a3cf19ee5f",
      "provider": "football_data",
      "provider_player_id": "28770",
      "photo_url": null,
      "club": null,
      "shirt_number": null,
      "height": null,
      "preferred_foot": null,
      "market_value": null,
      "market_value_eur": null,
      "rating": null,
      "date_of_birth": "2000-02-15",
      "nationality": "Uruguay",
      "position": "Defence",
      "data_quality_score": 20,
      "enrichment_status": "pending",
      "data_sources": {},
      "missing": 6,
      "score": 20
    },
    {
      "id": "7b81ebff-0d87-4971-9214-9e1fc026852a",
      "name": "Mathías Olivera",
      "team_id": "2c14696e-6656-4cd7-86c3-a1a3cf19ee5f",
      "provider": "football_data",
      "provider_player_id": "32754",
      "photo_url": null,
      "club": null,
      "shirt_number": null,
      "height": null,
      "preferred_foot": null,
      "market_value": null,
      "market_value_eur": null,
      "rating": null,
      "date_of_birth": "1997-10-31",
      "nationality": "Uruguay",
      "position": "Defence",
      "data_quality_score": 20,
      "enrichment_status": "pending",
      "data_sources": {},
      "missing": 6,
      "score": 20
    },
    {
      "id": "117224d2-b14c-4777-863b-4839937c16a8",
      "name": "Santiago Bueno",
      "team_id": "2c14696e-6656-4cd7-86c3-a1a3cf19ee5f",
      "provider": "football_data",
      "provider_player_id": "32767",
      "photo_url": null,
      "club": null,
      "shirt_number": null,
      "height": null,
      "preferred_foot": null,
      "market_value": null,
      "market_value_eur": null,
      "rating": null,
      "date_of_birth": "1998-11-09",
      "nationality": "Uruguay",
      "position": "Defence",
      "data_quality_score": 20,
      "enrichment_status": "pending",
      "data_sources": {},
      "missing": 6,
      "score": 20
    },
    {
      "id": "d225c3d5-cefc-462b-b644-3cb20b5470ae",
      "name": "José Giménez",
      "team_id": "2c14696e-6656-4cd7-86c3-a1a3cf19ee5f",
      "provider": "football_data",
      "provider_player_id": "213277",
      "photo_url": null,
      "club": null,
      "shirt_number": null,
      "height": null,
      "preferred_foot": null,
      "market_value": null,
      "market_value_eur": null,
      "rating": null,
      "date_of_birth": "1995-01-20",
      "nationality": "Uruguay",
      "position": "Defence",
      "data_quality_score": 20,
      "enrichment_status": "pending",
      "data_sources": {},
      "missing": 6,
      "score": 20
    },
    {
      "id": "b411d542-ec57-4737-8027-82187905aa53",
      "name": "Federico Valverde",
      "team_id": "2c14696e-6656-4cd7-86c3-a1a3cf19ee5f",
      "provider": "football_data",
      "provider_player_id": "96",
      "photo_url": null,
      "club": null,
      "shirt_number": null,
      "height": null,
      "preferred_foot": null,
      "market_value": null,
      "market_value_eur": null,
      "rating": null,
      "date_of_birth": "1998-07-22",
      "nationality": "Uruguay",
      "position": "Midfield",
      "data_quality_score": 20,
      "enrichment_status": "pending",
      "data_sources": {},
      "missing": 6,
      "score": 20
    },
    {
      "id": "b0d221d5-724e-4102-aa96-6a7a65b10069",
      "name": "Giorgian De Arrascaeta",
      "team_id": "2c14696e-6656-4cd7-86c3-a1a3cf19ee5f",
      "provider": "football_data",
      "provider_player_id": "1244",
      "photo_url": null,
      "club": null,
      "shirt_number": null,
      "height": null,
      "preferred_foot": null,
      "market_value": null,
      "market_value_eur": null,
      "rating": null,
      "date_of_birth": "1994-06-01",
      "nationality": "Uruguay",
      "position": "Midfield",
      "data_quality_score": 20,
      "enrichment_status": "pending",
      "data_sources": {},
      "missing": 6,
      "score": 20
    },
    {
      "id": "e6fd653f-fd23-4050-8956-d13a84fbc772",
      "name": "Rodrigo Bentancur",
      "team_id": "2c14696e-6656-4cd7-86c3-a1a3cf19ee5f",
      "provider": "football_data",
      "provider_player_id": "2041",
      "photo_url": null,
      "club": null,
      "shirt_number": null,
      "height": null,
      "preferred_foot": null,
      "market_value": null,
      "market_value_eur": null,
      "rating": null,
      "date_of_birth": "1997-06-25",
      "nationality": "Uruguay",
      "position": "Midfield",
      "data_quality_score": 20,
      "enrichment_status": "pending",
      "data_sources": {},
      "missing": 6,
      "score": 20
    },
    {
      "id": "d8bdb846-23cf-44b3-8c66-d8b1e83c13d8",
      "name": "Manuel Ugarte",
      "team_id": "2c14696e-6656-4cd7-86c3-a1a3cf19ee5f",
      "provider": "football_data",
      "provider_player_id": "28549",
      "photo_url": null,
      "club": null,
      "shirt_number": null,
      "height": null,
      "preferred_foot": null,
      "market_value": null,
      "market_value_eur": null,
      "rating": null,
      "date_of_birth": "2001-04-11",
      "nationality": "Uruguay",
      "position": "Midfield",
      "data_quality_score": 20,
      "enrichment_status": "pending",
      "data_sources": {},
      "missing": 6,
      "score": 20
    },
    {
      "id": "f12fa8fc-c7b9-49a3-9172-05358a527bec",
      "name": "Brian Rodríguez",
      "team_id": "2c14696e-6656-4cd7-86c3-a1a3cf19ee5f",
      "provider": "football_data",
      "provider_player_id": "28618",
      "photo_url": null,
      "club": null,
      "shirt_number": null,
      "height": null,
      "preferred_foot": null,
      "market_value": null,
      "market_value_eur": null,
      "rating": null,
      "date_of_birth": "2000-05-20",
      "nationality": "Uruguay",
      "position": "Midfield",
      "data_quality_score": 20,
      "enrichment_status": "pending",
      "data_sources": {},
      "missing": 6,
      "score": 20
    },
    {
      "id": "8f512fb2-09ff-43a1-aa00-c758814900ed",
      "name": "Rodrigo Zalazar",
      "team_id": "2c14696e-6656-4cd7-86c3-a1a3cf19ee5f",
      "provider": "football_data",
      "provider_player_id": "121007",
      "photo_url": null,
      "club": null,
      "shirt_number": null,
      "height": null,
      "preferred_foot": null,
      "market_value": null,
      "market_value_eur": null,
      "rating": null,
      "date_of_birth": "1999-08-12",
      "nationality": "Uruguay",
      "position": "Midfield",
      "data_quality_score": 20,
      "enrichment_status": "pending",
      "data_sources": {},
      "missing": 6,
      "score": 20
    },
    {
      "id": "40e5960a-6ed3-4a7d-b053-2ef19d60db5f",
      "name": "Facundo Pellistri",
      "team_id": "2c14696e-6656-4cd7-86c3-a1a3cf19ee5f",
      "provider": "football_data",
      "provider_player_id": "122506",
      "photo_url": null,
      "club": null,
      "shirt_number": null,
      "height": null,
      "preferred_foot": null,
      "market_value": null,
      "market_value_eur": null,
      "rating": null,
      "date_of_birth": "2001-12-20",
      "nationality": "Uruguay",
      "position": "Midfield",
      "data_quality_score": 20,
      "enrichment_status": "pending",
      "data_sources": {},
      "missing": 6,
      "score": 20
    },
    {
      "id": "61f9708a-5076-45ee-83e1-c1889f9312b4",
      "name": "Emiliano Martínez",
      "team_id": "2c14696e-6656-4cd7-86c3-a1a3cf19ee5f",
      "provider": "football_data",
      "provider_player_id": "130957",
      "photo_url": null,
      "club": null,
      "shirt_number": null,
      "height": null,
      "preferred_foot": null,
      "market_value": null,
      "market_value_eur": null,
      "rating": null,
      "date_of_birth": "1999-08-17",
      "nationality": "Uruguay",
      "position": "Midfield",
      "data_quality_score": 20,
      "enrichment_status": "pending",
      "data_sources": {},
      "missing": 6,
      "score": 20
    },
    {
      "id": "3621655f-935f-4dff-8066-f35877264a10",
      "name": "Juan Sanabria",
      "team_id": "2c14696e-6656-4cd7-86c3-a1a3cf19ee5f",
      "provider": "football_data",
      "provider_player_id": "152435",
      "photo_url": null,
      "club": null,
      "shirt_number": null,
      "height": null,
      "preferred_foot": null,
      "market_value": null,
      "market_value_eur": null,
      "rating": null,
      "date_of_birth": "2000-03-29",
      "nationality": "Uruguay",
      "position": "Midfield",
      "data_quality_score": 20,
      "enrichment_status": "pending",
      "data_sources": {},
      "missing": 6,
      "score": 20
    },
    {
      "id": "f87085d9-c8d9-49e0-903f-25733d0f24eb",
      "name": "Nicolas de la Cruz",
      "team_id": "2c14696e-6656-4cd7-86c3-a1a3cf19ee5f",
      "provider": "football_data",
      "provider_player_id": "168795",
      "photo_url": null,
      "club": null,
      "shirt_number": null,
      "height": null,
      "preferred_foot": null,
      "market_value": null,
      "market_value_eur": null,
      "rating": null,
      "date_of_birth": "1997-06-01",
      "nationality": "Uruguay",
      "position": "Midfield",
      "data_quality_score": 20,
      "enrichment_status": "pending",
      "data_sources": {},
      "missing": 6,
      "score": 20
    },
    {
      "id": "39ae561c-feb5-4195-9383-a1672dc52541",
      "name": "Rodrigo Aguirre",
      "team_id": "2c14696e-6656-4cd7-86c3-a1a3cf19ee5f",
      "provider": "football_data",
      "provider_player_id": "11206",
      "photo_url": null,
      "club": null,
      "shirt_number": null,
      "height": null,
      "preferred_foot": null,
      "market_value": null,
      "market_value_eur": null,
      "rating": null,
      "date_of_birth": "1994-10-01",
      "nationality": "Uruguay",
      "position": "Offence",
      "data_quality_score": 20,
      "enrichment_status": "pending",
      "data_sources": {},
      "missing": 6,
      "score": 20
    },
    {
      "id": "128e875b-4a8c-44d4-81a1-2bc80107711e",
      "name": "Darwin Núñez",
      "team_id": "2c14696e-6656-4cd7-86c3-a1a3cf19ee5f",
      "provider": "football_data",
      "provider_player_id": "28612",
      "photo_url": null,
      "club": null,
      "shirt_number": null,
      "height": null,
      "preferred_foot": null,
      "market_value": null,
      "market_value_eur": null,
      "rating": null,
      "date_of_birth": "1999-06-24",
      "nationality": "Uruguay",
      "position": "Offence",
      "data_quality_score": 20,
      "enrichment_status": "pending",
      "data_sources": {},
      "missing": 6,
      "score": 20
    },
    {
      "id": "0bc9d7f1-f241-438e-be51-a98a2d81546f",
      "name": "Federico Viñas",
      "team_id": "2c14696e-6656-4cd7-86c3-a1a3cf19ee5f",
      "provider": "football_data",
      "provider_player_id": "112678",
      "photo_url": null,
      "club": null,
      "shirt_number": null,
      "height": null,
      "preferred_foot": null,
      "market_value": null,
      "market_value_eur": null,
      "rating": null,
      "date_of_birth": "1998-06-30",
      "nationality": "Uruguay",
      "position": "Offence",
      "data_quality_score": 20,
      "enrichment_status": "pending",
      "data_sources": {},
      "missing": 6,
      "score": 20
    },
    {
      "id": "5569b70e-08fc-4bb9-93c2-9bd4f3917aae",
      "name": "Oliver Baumann",
      "team_id": "b11040ed-0acf-43c2-932f-478baf0c22f7",
      "provider": "football_data",
      "provider_player_id": "316",
      "photo_url": null,
      "club": null,
      "shirt_number": null,
      "height": null,
      "preferred_foot": null,
      "market_value": null,
      "market_value_eur": null,
      "rating": null,
      "date_of_birth": "1990-06-02",
      "nationality": "Germany",
      "position": "Goalkeeper",
      "data_quality_score": 20,
      "enrichment_status": "pending",
      "data_sources": {},
      "missing": 6,
      "score": 20
    },
    {
      "id": "8bbaad73-2ecc-4e47-93b4-86777170e954",
      "name": "Manuel Neuer",
      "team_id": "b11040ed-0acf-43c2-932f-478baf0c22f7",
      "provider": "football_data",
      "provider_player_id": "341",
      "photo_url": null,
      "club": null,
      "shirt_number": null,
      "height": null,
      "preferred_foot": null,
      "market_value": null,
      "market_value_eur": null,
      "rating": null,
      "date_of_birth": "1986-03-27",
      "nationality": "Germany",
      "position": "Goalkeeper",
      "data_quality_score": 20,
      "enrichment_status": "pending",
      "data_sources": {},
      "missing": 6,
      "score": 20
    },
    {
      "id": "b8b17aed-1c92-4cb0-aa50-390d7beeec72",
      "name": "Alexander Nübel",
      "team_id": "b11040ed-0acf-43c2-932f-478baf0c22f7",
      "provider": "football_data",
      "provider_player_id": "6491",
      "photo_url": null,
      "club": null,
      "shirt_number": null,
      "height": null,
      "preferred_foot": null,
      "market_value": null,
      "market_value_eur": null,
      "rating": null,
      "date_of_birth": "1996-09-30",
      "nationality": "Germany",
      "position": "Goalkeeper",
      "data_quality_score": 20,
      "enrichment_status": "pending",
      "data_sources": {},
      "missing": 6,
      "score": 20
    },
    {
      "id": "d0e7b92b-aa46-4676-8dec-b29317ea9e85",
      "name": "Jonathan Tah",
      "team_id": "b11040ed-0acf-43c2-932f-478baf0c22f7",
      "provider": "football_data",
      "provider_player_id": "149",
      "photo_url": null,
      "club": null,
      "shirt_number": null,
      "height": null,
      "preferred_foot": null,
      "market_value": null,
      "market_value_eur": null,
      "rating": null,
      "date_of_birth": "1996-02-11",
      "nationality": "Germany",
      "position": "Defence",
      "data_quality_score": 20,
      "enrichment_status": "pending",
      "data_sources": {},
      "missing": 6,
      "score": 20
    },
    {
      "id": "39b358c0-959f-4912-9c20-5928a8f7e494",
      "name": "Waldemar Anton",
      "team_id": "b11040ed-0acf-43c2-932f-478baf0c22f7",
      "provider": "football_data",
      "provider_player_id": "379",
      "photo_url": null,
      "club": null,
      "shirt_number": null,
      "height": null,
      "preferred_foot": null,
      "market_value": null,
      "market_value_eur": null,
      "rating": null,
      "date_of_birth": "1996-07-20",
      "nationality": "Germany",
      "position": "Defence",
      "data_quality_score": 20,
      "enrichment_status": "pending",
      "data_sources": {},
      "missing": 6,
      "score": 20
    },
    {
      "id": "f060cf39-83ec-4160-a10e-d6d9d4f24655",
      "name": "Antonio Rüdiger",
      "team_id": "b11040ed-0acf-43c2-932f-478baf0c22f7",
      "provider": "football_data",
      "provider_player_id": "3177",
      "photo_url": null,
      "club": null,
      "shirt_number": null,
      "height": null,
      "preferred_foot": null,
      "market_value": null,
      "market_value_eur": null,
      "rating": null,
      "date_of_birth": "1993-03-03",
      "nationality": "Germany",
      "position": "Defence",
      "data_quality_score": 20,
      "enrichment_status": "pending",
      "data_sources": {},
      "missing": 6,
      "score": 20
    },
    {
      "id": "2b58f4ed-f95b-411b-a5f3-fea8fc9bca8c",
      "name": "David Raum",
      "team_id": "b11040ed-0acf-43c2-932f-478baf0c22f7",
      "provider": "football_data",
      "provider_player_id": "9905",
      "photo_url": null,
      "club": null,
      "shirt_number": null,
      "height": null,
      "preferred_foot": null,
      "market_value": null,
      "market_value_eur": null,
      "rating": null,
      "date_of_birth": "1998-04-22",
      "nationality": "Germany",
      "position": "Defence",
      "data_quality_score": 20,
      "enrichment_status": "pending",
      "data_sources": {},
      "missing": 6,
      "score": 20
    },
    {
      "id": "2df7ec07-c3e7-4dfc-be40-91531f474dfc",
      "name": "Nico Schlotterbeck",
      "team_id": "b11040ed-0acf-43c2-932f-478baf0c22f7",
      "provider": "football_data",
      "provider_player_id": "75539",
      "photo_url": null,
      "club": null,
      "shirt_number": null,
      "height": null,
      "preferred_foot": null,
      "market_value": null,
      "market_value_eur": null,
      "rating": null,
      "date_of_birth": "1999-12-01",
      "nationality": "Germany",
      "position": "Defence",
      "data_quality_score": 20,
      "enrichment_status": "pending",
      "data_sources": {},
      "missing": 6,
      "score": 20
    },
    {
      "id": "a8394a3b-2548-44b7-a2e9-8bfa6e194706",
      "name": "Malick Thiaw",
      "team_id": "b11040ed-0acf-43c2-932f-478baf0c22f7",
      "provider": "football_data",
      "provider_player_id": "142732",
      "photo_url": null,
      "club": null,
      "shirt_number": null,
      "height": null,
      "preferred_foot": null,
      "market_value": null,
      "market_value_eur": null,
      "rating": null,
      "date_of_birth": "2001-08-08",
      "nationality": "Germany",
      "position": "Defence",
      "data_quality_score": 20,
      "enrichment_status": "pending",
      "data_sources": {},
      "missing": 6,
      "score": 20
    },
    {
      "id": "bb0d6034-e798-4445-a555-f39de1ec6c79",
      "name": "Nathaniel Brown",
      "team_id": "b11040ed-0acf-43c2-932f-478baf0c22f7",
      "provider": "football_data",
      "provider_player_id": "184533",
      "photo_url": null,
      "club": null,
      "shirt_number": null,
      "height": null,
      "preferred_foot": null,
      "market_value": null,
      "market_value_eur": null,
      "rating": null,
      "date_of_birth": "2003-06-16",
      "nationality": "Germany",
      "position": "Defence",
      "data_quality_score": 20,
      "enrichment_status": "pending",
      "data_sources": {},
      "missing": 6,
      "score": 20
    },
    {
      "id": "66ed554b-7110-449c-aea4-ea0f92a43552",
      "name": "Nadiem Amiri",
      "team_id": "b11040ed-0acf-43c2-932f-478baf0c22f7",
      "provider": "football_data",
      "provider_player_id": "320",
      "photo_url": null,
      "club": null,
      "shirt_number": null,
      "height": null,
      "preferred_foot": null,
      "market_value": null,
      "market_value_eur": null,
      "rating": null,
      "date_of_birth": "1996-10-27",
      "nationality": "Germany",
      "position": "Midfield",
      "data_quality_score": 20,
      "enrichment_status": "pending",
      "data_sources": {},
      "missing": 6,
      "score": 20
    },
    {
      "id": "b0df657b-a711-42bf-98b0-350c7eebfc20",
      "name": "Joshua Kimmich",
      "team_id": "b11040ed-0acf-43c2-932f-478baf0c22f7",
      "provider": "football_data",
      "provider_player_id": "359",
      "photo_url": null,
      "club": null,
      "shirt_number": null,
      "height": null,
      "preferred_foot": null,
      "market_value": null,
      "market_value_eur": null,
      "rating": null,
      "date_of_birth": "1995-02-08",
      "nationality": "Germany",
      "position": "Midfield",
      "data_quality_score": 20,
      "enrichment_status": "pending",
      "data_sources": {},
      "missing": 6,
      "score": 20
    },
    {
      "id": "4139c64c-44c2-4987-ae85-7a70efc8663c",
      "name": "Leon Goretzka",
      "team_id": "b11040ed-0acf-43c2-932f-478baf0c22f7",
      "provider": "football_data",
      "provider_player_id": "3181",
      "photo_url": null,
      "club": null,
      "shirt_number": null,
      "height": null,
      "preferred_foot": null,
      "market_value": null,
      "market_value_eur": null,
      "rating": null,
      "date_of_birth": "1995-02-06",
      "nationality": "Germany",
      "position": "Midfield",
      "data_quality_score": 20,
      "enrichment_status": "pending",
      "data_sources": {},
      "missing": 6,
      "score": 20
    },
    {
      "id": "8ae054cc-4b5b-42c1-9243-ca3004304999",
      "name": "Pascal Groß",
      "team_id": "b11040ed-0acf-43c2-932f-478baf0c22f7",
      "provider": "football_data",
      "provider_player_id": "8273",
      "photo_url": null,
      "club": null,
      "shirt_number": null,
      "height": null,
      "preferred_foot": null,
      "market_value": null,
      "market_value_eur": null,
      "rating": null,
      "date_of_birth": "1991-06-15",
      "nationality": "Germany",
      "position": "Midfield",
      "data_quality_score": 20,
      "enrichment_status": "pending",
      "data_sources": {},
      "missing": 6,
      "score": 20
    },
    {
      "id": "a19071f9-9d6b-49f6-8659-bfd5926e5f5b",
      "name": "Florian Wirtz",
      "team_id": "b11040ed-0acf-43c2-932f-478baf0c22f7",
      "provider": "football_data",
      "provider_player_id": "19334",
      "photo_url": null,
      "club": null,
      "shirt_number": null,
      "height": null,
      "preferred_foot": null,
      "market_value": null,
      "market_value_eur": null,
      "rating": null,
      "date_of_birth": "2003-05-03",
      "nationality": "Germany",
      "position": "Midfield",
      "data_quality_score": 20,
      "enrichment_status": "pending",
      "data_sources": {},
      "missing": 6,
      "score": 20
    },
    {
      "id": "11994183-c9fa-4bc2-8ce7-eaf75e540c19",
      "name": "Felix Kalu Nmecha",
      "team_id": "b11040ed-0acf-43c2-932f-478baf0c22f7",
      "provider": "football_data",
      "provider_player_id": "101074",
      "photo_url": null,
      "club": null,
      "shirt_number": null,
      "height": null,
      "preferred_foot": null,
      "market_value": null,
      "market_value_eur": null,
      "rating": null,
      "date_of_birth": "2000-10-10",
      "nationality": "Germany",
      "position": "Midfield",
      "data_quality_score": 20,
      "enrichment_status": "pending",
      "data_sources": {},
      "missing": 6,
      "score": 20
    },
    {
      "id": "3f986188-cce0-42e9-854b-f2f545235ca2",
      "name": "Angelo Stiller",
      "team_id": "b11040ed-0acf-43c2-932f-478baf0c22f7",
      "provider": "football_data",
      "provider_player_id": "128565",
      "photo_url": null,
      "club": null,
      "shirt_number": null,
      "height": null,
      "preferred_foot": null,
      "market_value": null,
      "market_value_eur": null,
      "rating": null,
      "date_of_birth": "2001-04-04",
      "nationality": "Germany",
      "position": "Midfield",
      "data_quality_score": 20,
      "enrichment_status": "pending",
      "data_sources": {},
      "missing": 6,
      "score": 20
    },
    {
      "id": "594f20ea-1591-4b64-a363-5d493ff37c81",
      "name": "Jamal Musiala",
      "team_id": "b11040ed-0acf-43c2-932f-478baf0c22f7",
      "provider": "football_data",
      "provider_player_id": "144393",
      "photo_url": null,
      "club": null,
      "shirt_number": null,
      "height": null,
      "preferred_foot": null,
      "market_value": null,
      "market_value_eur": null,
      "rating": null,
      "date_of_birth": "2003-02-26",
      "nationality": "Germany",
      "position": "Midfield",
      "data_quality_score": 20,
      "enrichment_status": "pending",
      "data_sources": {},
      "missing": 6,
      "score": 20
    },
    {
      "id": "8eeeb902-3875-47c0-9a81-8257f9865317",
      "name": "Aleksandar Pavlović",
      "team_id": "b11040ed-0acf-43c2-932f-478baf0c22f7",
      "provider": "football_data",
      "provider_player_id": "202665",
      "photo_url": null,
      "club": null,
      "shirt_number": null,
      "height": null,
      "preferred_foot": null,
      "market_value": null,
      "market_value_eur": null,
      "rating": null,
      "date_of_birth": "2004-05-03",
      "nationality": "Germany",
      "position": "Midfield",
      "data_quality_score": 20,
      "enrichment_status": "pending",
      "data_sources": {},
      "missing": 6,
      "score": 20
    },
    {
      "id": "1b35d03c-858f-4f36-928f-8a485a19d7c5",
      "name": "Lennart Karl",
      "team_id": "b11040ed-0acf-43c2-932f-478baf0c22f7",
      "provider": "football_data",
      "provider_player_id": "277592",
      "photo_url": null,
      "club": null,
      "shirt_number": null,
      "height": null,
      "preferred_foot": null,
      "market_value": null,
      "market_value_eur": null,
      "rating": null,
      "date_of_birth": "2008-02-22",
      "nationality": "Germany",
      "position": "Midfield",
      "data_quality_score": 20,
      "enrichment_status": "pending",
      "data_sources": {},
      "missing": 6,
      "score": 20
    },
    {
      "id": "62196c85-93d7-4c2a-aade-16c41c5438d1",
      "name": "Kai Havertz",
      "team_id": "b11040ed-0acf-43c2-932f-478baf0c22f7",
      "provider": "football_data",
      "provider_player_id": "171",
      "photo_url": null,
      "club": null,
      "shirt_number": null,
      "height": null,
      "preferred_foot": null,
      "market_value": null,
      "market_value_eur": null,
      "rating": null,
      "date_of_birth": "1999-06-11",
      "nationality": "Germany",
      "position": "Offence",
      "data_quality_score": 20,
      "enrichment_status": "pending",
      "data_sources": {},
      "missing": 6,
      "score": 20
    },
    {
      "id": "1b11f74e-b1a3-499a-bdbe-2faaf8a5d11c",
      "name": "Leroy Sané",
      "team_id": "b11040ed-0acf-43c2-932f-478baf0c22f7",
      "provider": "football_data",
      "provider_player_id": "3184",
      "photo_url": null,
      "club": null,
      "shirt_number": null,
      "height": null,
      "preferred_foot": null,
      "market_value": null,
      "market_value_eur": null,
      "rating": null,
      "date_of_birth": "1996-01-11",
      "nationality": "Germany",
      "position": "Offence",
      "data_quality_score": 20,
      "enrichment_status": "pending",
      "data_sources": {},
      "missing": 6,
      "score": 20
    }
  ],
  "duplicateGroups": [
    {
      "name": "emiliano martinez",
      "count": 2,
      "players": [
        {
          "id": "61f9708a-5076-45ee-83e1-c1889f9312b4",
          "name": "Emiliano Martínez",
          "team_id": "2c14696e-6656-4cd7-86c3-a1a3cf19ee5f",
          "provider": "football_data",
          "provider_player_id": "130957",
          "photo_url": null,
          "club": null,
          "shirt_number": null,
          "height": null,
          "preferred_foot": null,
          "market_value": null,
          "market_value_eur": null,
          "rating": null,
          "date_of_birth": "1999-08-17",
          "nationality": "Uruguay",
          "position": "Midfield",
          "data_quality_score": 20,
          "enrichment_status": "pending",
          "data_sources": {}
        },
        {
          "id": "171a0c7f-53db-47d6-a201-334609587cfd",
          "name": "Emiliano Martínez",
          "team_id": "09f42c00-65ed-47f2-9391-d47f879d1a75",
          "provider": "football_data",
          "provider_player_id": "3141",
          "photo_url": null,
          "club": null,
          "shirt_number": null,
          "height": null,
          "preferred_foot": null,
          "market_value": null,
          "market_value_eur": null,
          "rating": null,
          "date_of_birth": "1992-09-02",
          "nationality": "Argentina",
          "position": "Goalkeeper",
          "data_quality_score": 20,
          "enrichment_status": "pending",
          "data_sources": {}
        }
      ]
    }
  ],
  "withoutExternalId": 0,
  "missingFieldsRank": [
    {
      "field": "market_value",
      "dbKey": "market_value",
      "count": 6,
      "pct": 0.6
    },
    {
      "field": "preferred_foot",
      "dbKey": "preferred_foot",
      "count": 22,
      "pct": 2.2
    },
    {
      "field": "shirt_number",
      "dbKey": "shirt_number",
      "count": 27,
      "pct": 2.7
    },
    {
      "field": "height",
      "dbKey": "height",
      "count": 27,
      "pct": 2.7
    },
    {
      "field": "photo_url",
      "dbKey": "photo_url",
      "count": 30,
      "pct": 3
    },
    {
      "field": "club",
      "dbKey": "club",
      "count": 35,
      "pct": 3.5
    },
    {
      "field": "nationality",
      "dbKey": "nationality",
      "count": 998,
      "pct": 99.8
    },
    {
      "field": "birth_date",
      "dbKey": "date_of_birth",
      "count": 1000,
      "pct": 100
    },
    {
      "field": "position",
      "dbKey": "position",
      "count": 1000,
      "pct": 100
    }
  ]
}